Workbook

Sheet Übersicht
B2: Fliesen Krause – Monatsübersicht Oktober 2026
B3: automatisch – hier bitte nichts eintragen
B5: Stunden Oktober | D5: ='Stunden Oktober'!H31 -> 141.5
B6: Lohnkosten Oktober | D6: ='Stunden Oktober'!I31 -> 6700
B7: Rechnungen offen (brutto) | D7: =Aufträge!H14 -> 316576
B8: Umsatz netto 2026 | D8: =Aufträge!E13 -> 50660
B9: Lagerwert | D9: =Lager!G19 -> 1499.9
B10: Artikel nachbestellen | D10: =COUNTIF(Lager!H4:H17,"JA") -> 4

Sheet Stunden Oktober
B1: Fliesen Krause GmbH · Gneisenaustr. 22 · Berlin
B2: Stundenerfassung Oktober 2026 – bitte jeden Freitag ausfüllen!
B4: Datum | C4: Wer / Wo | E4: Arbeitszeit | H4: Stunden | I4: Lohn € | J4: Tätigkeit / Notiz | L4: Mitarbeiter | M4: Satz €/Std.
C5: Mitarbeiter | D5: Baustelle | E5: Beginn | F5: Ende | G5: Pause (Min.) | L5: Mehmet | M5: 52
B6: — KW 40 — | L6: Kevin | M6: 45
B7: 46296 | C7: Mehmet | D7: Bad Schneider | E7: 0.29166667 | F7: 0.66666667 | G7: 30 | H7: =IFERROR(ROUND((F7-E7)*24-IF(ISNUMBER(G7),G7,0)/60,2),"") -> 8.5 | I7: =IF(ISNUMBER(H7),ROUND(H7*VLOOKUP(TRIM(C7),$L$5:$M$8,2,FALSE()),2),"") -> 442 | J7: Wand gefliest | L7: Jonas | M7: 45
B8: 46296 | C8: Kevin | D8: Bad Schneider | E8: 0.29166667 | F8: 0.64583333 | G8: 30 | H8: =IFERROR(ROUND((F8-E8)*24-IF(ISNUMBER(G8),G8,0)/60,2),"") -> 8 | I8: =IF(ISNUMBER(H8),ROUND(H8*VLOOKUP(TRIM(C8),$L$5:$M$8,2,FALSE()),2),"") -> 360 | J8: Estrich geprüft | L8: Ayşe | M8: 38
B9: 46297 | C9: Mehmet | D9: Bad Schneider | E9: 0.29166667 | F9: 0.625 | G9: 30 | H9: =IFERROR(ROUND((F9-E9)*24-IF(ISNUMBER(G9),G9,0)/60,2),"") -> 7.5 | I9: =IF(ISNUMBER(H9),ROUND(H9*VLOOKUP(TRIM(C9),$L$5:$M$8,2,FALSE()),2),"") -> 390 | J9: Fugen
B10: 46297 | C10: Ayşe | D10: Büro / Lager | E10: 0.33333333 | F10: 0.52083333 | G10: 0 | H10: =IFERROR(ROUND((F10-E10)*24-IF(ISNUMBER(G10),G10,0)/60,2),"") -> 4.5 | I10: =IF(ISNUMBER(H10),ROUND(H10*VLOOKUP(TRIM(C10),$L$5:$M$8,2,FALSE()),2),"") -> 171 | J10: Bestellung Kaiser | L10: Sätze ab 01.07.2026
B11: Zwischensumme KW 40 | H11: =SUBTOTAL(9,H7:H10) -> 28.5 | I11: =SUBTOTAL(9,I7:I10) -> 1363
B12: — KW 41 —
B13: 46300 | C13: Jonas | D13: Praxis Dr. Hahn | E13: 0.29166667 | F13: 0.6875 | G13: 45 | H13: =IFERROR(ROUND((F13-E13)*24-IF(ISNUMBER(G13),G13,0)/60,2),"") -> 8.75 | I13: =IF(ISNUMBER(H13),ROUND(H13*VLOOKUP(TRIM(C13),$L$5:$M$8,2,FALSE()),2),"") -> 393.75 | J13: Boden 60x60
B14: 06.10.26 | C14: Mehmet | D14: Küche Yılmaz | E14: 7:00 | F14: 16:00 | G14: 30 min | H14: =IFERROR(ROUND((F14-E14)*24-IF(ISNUMBER(G14),G14,0)/60,2),"") -> 9 | I14: =IF(ISNUMBER(H14),ROUND(H14*VLOOKUP(TRIM(C14),$L$5:$M$8,2,FALSE()),2),"") -> 468 | J14: Fliesenspiegel
B15: 46301 | C15: Kevin | D15: Praxis Dr. Hahn | E15: 0.29166667 | F15: 0.70833333 | G15: 30 | H15: =IFERROR(ROUND((F15-E15)*24-IF(ISNUMBER(G15),G15,0)/60,2),"") -> 9.5 | I15: =IF(ISNUMBER(H15),ROUND(H15*VLOOKUP(TRIM(C15),$L$5:$M$8,2,FALSE()),2),"") -> 427.5 | J15: Sockel
B16: 46302 | C16: Jonas | D16: Praxis Dr. Hahn | E16: 0.29166667 | F16: 0.64583333 | G16: 30 | H16: =IFERROR(ROUND((F16-E16)*24-IF(ISNUMBER(G16),G16,0)/60,2),"") -> 8 | I16: =IF(ISNUMBER(H16),ROUND(H16*VLOOKUP(TRIM(C16),$L$5:$M$8,2,FALSE()),2),"") -> 360
B17: 46303 | C17: Kevin | D17: Küche Yılmaz | E17: 0.27083333 | F17: 0.64583333 | G17: 15 | H17: =IFERROR(ROUND((F17-E17)*24-IF(ISNUMBER(G17),G17,0)/60,2),"") -> 8.75 | I17: =IF(ISNUMBER(H17),ROUND(H17*VLOOKUP(TRIM(C17),$L$5:$M$8,2,FALSE()),2),"") -> 393.75 | J17: Silikon
B18: 46304 | C18: Ayşe | D18: Büro / Lager | E18: 0.33333333 | F18: 0.54166667 | G18: 0 | H18: =IFERROR(ROUND((F18-E18)*24-IF(ISNUMBER(G18),G18,0)/60,2),"") -> 5 | I18: =IF(ISNUMBER(H18),ROUND(H18*VLOOKUP(TRIM(C18),$L$5:$M$8,2,FALSE()),2),"") -> 190 | J18: Inventur
B19: Zwischensumme KW 41 | H19: =SUBTOTAL(9,H13:H18) -> 49 | I19: =SUBTOTAL(9,I13:I18) -> 2233
B20: — KW 42 —
B21: 46307 | C21: Jonas | D21: Neubau Weber | E21: 0.29166667 | F21: 0.77083333 | G21: 30 | H21: =IFERROR(ROUND((F21-E21)*24-IF(ISNUMBER(G21),G21,0)/60,2),"") -> 11 | I21: =IF(ISNUMBER(H21),ROUND(H21*VLOOKUP(TRIM(C21),$L$5:$M$8,2,FALSE()),2),"") -> 495 | J21: Estrich noch feucht – Überstunden
B22: 46308 | C22: Jonas | D22: Neubau Weber | E22: 0.20833333 | F22: 0.54166667 | G22: 30 | H22: =IFERROR(ROUND((F22-E22)*24-IF(ISNUMBER(G22),G22,0)/60,2),"") -> 7.5 | I22: =IF(ISNUMBER(H22),ROUND(H22*VLOOKUP(TRIM(C22),$L$5:$M$8,2,FALSE()),2),"") -> 337.5 | J22: früh wegen Lieferung
B23: 46308 | C23: Mehmet | D23: Neubau Weber | E23: 0.29166667 | F23: 0.66666667 | G23: 30 | H23: =IFERROR(ROUND((F23-E23)*24-IF(ISNUMBER(G23),G23,0)/60,2),"") -> 8.5 | I23: =IF(ISNUMBER(H23),ROUND(H23*VLOOKUP(TRIM(C23),$L$5:$M$8,2,FALSE()),2),"") -> 442 | J23: Bad OG
B24: 46309 | C24: mehmet | D24: Neubau Weber | E24: 0.29166667 | F24: 0.66666667 | G24: 30 | H24: =IFERROR(ROUND((F24-E24)*24-IF(ISNUMBER(G24),G24,0)/60,2),"") -> 8.5 | I24: =IF(ISNUMBER(H24),ROUND(H24*VLOOKUP(TRIM(C24),$L$5:$M$8,2,FALSE()),2),"") -> 442 | J24: Bad OG
B25: 46310 | C25: Kevin | D25: Bad Schneider | E25: 0.29166667 | F25: 0.5 | G25: 0 | H25: =IFERROR(ROUND((F25-E25)*24-IF(ISNUMBER(G25),G25,0)/60,2),"") -> 5 | I25: =IF(ISNUMBER(H25),ROUND(H25*VLOOKUP(TRIM(C25),$L$5:$M$8,2,FALSE()),2),"") -> 225 | J25: Nacharbeit Silikon
B26: 46311 | C26: Mehmet | D26: Neubau Weber | E26: 0.29166667 | F26: 0.58333333 | G26: 30 | H26: =IFERROR(ROUND((F26-E26)*24-IF(ISNUMBER(G26),G26,0)/60,2),"") -> 6.5 | I26: =IF(ISNUMBER(H26),ROUND(H26*VLOOKUP(TRIM(C26),$L$5:$M$8,2,FALSE()),2),"") -> 338 | J26: Treppe
B27: Zwischensumme KW 42 | H27: =SUBTOTAL(9,H21:H26) -> 47 | I27: =SUBTOTAL(9,I21:I26) -> 2279.5
B28: — KW 43 —
B29: 46314 | C29: Mehmet | D29: Neubau Weber | E29: 0.29166667 | F29: 0.66666667 | G29: 30 | H29: =IFERROR(ROUND((F29-E29)*24-IF(ISNUMBER(G29),G29,0)/60,2),"") -> 8.5 | I29: =IF(ISNUMBER(H29),ROUND(H29*VLOOKUP(TRIM(C29),$L$5:$M$8,2,FALSE()),2),"") -> 442 | J29: Bad EG
B30: 46314 | C30: Kevin | D30: Neubau Weber | E30: 0.29166667 | F30: 0.66666667 | G30: 30 | H30: =IFERROR(ROUND((F30-E30)*24-IF(ISNUMBER(G30),G30,0)/60,2),"") -> 8.5 | I30: =IF(ISNUMBER(H30),ROUND(H30*VLOOKUP(TRIM(C30),$L$5:$M$8,2,FALSE()),2),"") -> 382.5 | J30: Bad EG
B31: GESAMT Oktober | H31: =SUBTOTAL(9,H6:H30) -> 141.5 | I31: =SUBTOTAL(9,I6:I30) -> 6700
B33: Stand: | C33: 46314

Sheet Kunden
A1: Kd-Nr | B1: Name | C1: Zahlungsziel | D1: E-Mail
A2: 101 | B2: Becker, Thomas | C2: 14 | D2: t.becker@example.de
A3: 102 | B3: Yılmaz GbR | C3: 30 | D3: info@yilmaz.example
A4: 103 | B4: Praxis Dr. Hahn | C4: 10 | D4: praxis@hahn.example
A5: 104 | B5: Weber Bau GmbH | C5: 30 | D5: rechnung@weber-bau.example
A6: 105 | B6: Schneider, Anna | C6: 14 | D6: a.schneider@example.de
A7: 106 | B7: Hausverwaltung Lindner | C7: 21 | D7: buchhaltung@lindner.example

Sheet Aufträge
A1: Aufträge und Rechnungen 2026
A3: Auftrags-Nr | B3: Kd-Nr | C3: Kunde | D3: Baustelle | E3: Netto € | F3: MwSt-Satz | G3: MwSt € | H3: Brutto € | I3: Rechnung am | J3: Fällig am | K3: Status | L3: bezahlt am
A4: 2026-028 | B4: 105 | C4: =IFERROR(VLOOKUP(B4,Kunden!$A:$D,2,FALSE()),"??? unbekannt") -> Schneider, Anna | D4: Bad Schneider | E4: 6420 | F4: 0.19 | G4: =IFERROR(E4*F4,0) -> 1219.8 | H4: =IFERROR(E4+G4,E4) -> 7639.8 | I4: 46275 | J4: =IF(I4="","",I4+IFERROR(VLOOKUP(B4,Kunden!$A:$C,3,FALSE()),14)) -> 46289 | K4: bezahlt | L4: 46287
A5: 2026-029 | B5: 101 | C5: =IFERROR(VLOOKUP(B5,Kunden!$A:$D,2,FALSE()),"??? unbekannt") -> Becker, Thomas | D5: Gäste-WC Becker | E5: 2380 | F5: 0.19 | G5: =IFERROR(E5*F5,0) -> 452.2 | H5: =IFERROR(E5+G5,E5) -> 2832.2 | I5: 46290 | J5: =IF(I5="","",I5+IFERROR(VLOOKUP(B5,Kunden!$A:$C,3,FALSE()),14)) -> 46304 | K5: offen
A6: 2026-030 | B6: 103 | C6: =IFERROR(VLOOKUP(B6,Kunden!$A:$D,2,FALSE()),"??? unbekannt") -> Praxis Dr. Hahn | D6: Praxis Dr. Hahn | E6: 9850 | F6: 0.19 | G6: =IFERROR(E6*F6,0) -> 1871.5 | H6: =IFERROR(E6+G6,E6) -> 11721.5 | I6: 46297 | J6: =IF(I6="","",I6+IFERROR(VLOOKUP(B6,Kunden!$A:$C,3,FALSE()),14)) -> 46307 | K6: offen
A7: 2026-031 | B7: 102 | C7: =IFERROR(VLOOKUP(B7,Kunden!$A:$D,2,FALSE()),"??? unbekannt") -> Yılmaz GbR | D7: Küche Yılmaz | E7: 3120 | F7: 0.19 | G7: =IFERROR(E7*F7,0) -> 592.8 | H7: =IFERROR(E7+G7,E7) -> 3712.8 | I7: 46304 | J7: =IF(I7="","",I7+IFERROR(VLOOKUP(B7,Kunden!$A:$C,3,FALSE()),14)) -> 46334 | K7: Teilzahlung
A8: 2026-031 | B8: 106 | C8: =IFERROR(VLOOKUP(B8,Kunden!$A:$D,2,FALSE()),"??? unbekannt") -> Hausverwaltung Lindner | D8: Treppenhaus Lindner | E8: 4.250,00 | F8: 0.19 | G8: =IFERROR(E8*F8,0) -> 0 | H8: =IFERROR(E8+G8,E8) -> 4.250,00 | I8: 46307 | J8: =IF(I8="","",I8+IFERROR(VLOOKUP(B8,Kunden!$A:$C,3,FALSE()),14)) -> 46328 | K8: offen
A9: 2026-033 | B9: 104 | C9: =IFERROR(VLOOKUP(B9,Kunden!$A:$D,2,FALSE()),"??? unbekannt") -> Weber Bau GmbH | D9: Neubau Weber (Abschlag 1) | E9: 15000 | F9: 19 | G9: =IFERROR(E9*F9,0) -> 285000 | H9: =IFERROR(E9+G9,E9) -> 300000 | I9: 46309 | J9: =IF(I9="","",I9+IFERROR(VLOOKUP(B9,Kunden!$A:$C,3,FALSE()),14)) -> 46339 | K9: offen
A10: 2026-034 | B10: 107 | C10: =IFERROR(VLOOKUP(B10,Kunden!$A:$D,2,FALSE()),"??? unbekannt") -> ??? unbekannt | D10: Balkon Krüger | E10: 1890 | F10: 0.07 | G10: =IFERROR(E10*F10,0) -> 132.3 | H10: =IFERROR(E10+G10,E10) -> 2022.3 | I10: 46310 | J10: =IF(I10="","",I10+IFERROR(VLOOKUP(B10,Kunden!$A:$C,3,FALSE()),14)) -> 46324 | K10: offen
A11: 2026-035 | B11: 104 | C11: =IFERROR(VLOOKUP(B11,Kunden!$A:$D,2,FALSE()),"??? unbekannt") -> Weber Bau GmbH | D11: Neubau Weber (Abschlag 2) | E11: 12000 | F11: 0.19 | G11: =IFERROR(E11*F11,0) -> 2280 | H11: =IFERROR(E11+G11,E11) -> 14280 | J11: =IF(I11="","",I11+IFERROR(VLOOKUP(B11,Kunden!$A:$C,3,FALSE()),14)) | K11: Angebot
D13: Summe | E13: =SUM(E4:E11) -> 50660 | G13: =SUM(G4:G11) -> 291548.6 | H13: =SUM(H4:H11) -> 342208.6
D14: davon offen: | H14: =SUMIF(K4:K11,"offen",H4:H11) -> 316576

Sheet Lager
A1: Lagerliste Werkstatt | F1: gezählt: 09.10. (Ayşe)
A3: Art.-Nr | B3: Artikel | C3: Bestand | D3: Einheit | E3: Mindestbestand | F3: EK-Preis € | G3: Wert € | H3: Nachbestellen | I3: Lieferant
A4: A-1001 | B4: Fliesenkleber C2TE 25 kg | C4: 14 | D4: Sack | E4: 10 | F4: 14.9 | G4: =IFERROR(C4*F4,"") -> 208.6 | H4: =IF(AND(ISNUMBER(C4),C4<E4),"JA","") | I4: Baustoff Kaiser
A5: A-1002 | B5: Flexkleber S1 25 kg | C5: 4 | D5: Sack | E5: 8 | F5: 17.5 | G5: =IFERROR(C5*F5,"") -> 70 | H5: =IF(AND(ISNUMBER(C5),C5<E5),"JA","") -> JA | I5: Baustoff Kaiser
A6: A-1010 | B6: Fugenmörtel grau 5 kg | C6: 9 | D6: Eimer | E6: 6 | F6: 11.4 | G6: =IFERROR(C6*F6,"") -> 102.6 | H6: =IF(AND(ISNUMBER(C6),C6<E6),"JA","") | I6: Weber KG
A7: A-1011 | B7: Fugenmörtel anthrazit 5 kg | C7: 2 | D7: Eimer | E7: 4 | F7: 12.3 | G7: =IFERROR(C7*F7,"") -> 24.6 | H7: =IF(AND(ISNUMBER(C7),C7<E7),"JA","") -> JA | I7: Weber KG
A8: A-1020 | B8: Silikon sanitär weiß | C8: 18 | D8: Kartusche | E8: 12 | F8: 6.2 | G8: =IFERROR(C8*F8,"") -> 111.6 | H8: =IF(AND(ISNUMBER(C8),C8<E8),"JA","") | I8: Baustoff Kaiser
A9: A-1021 | B9: Silikon sanitär grau | C9: 5 | D9: Kartusche | E9: 12 | F9: 6,20 | G9: =IFERROR(C9*F9,"") | H9: =IF(AND(ISNUMBER(C9),C9<E9),"JA","") -> JA | I9: Baustoff Kaiser
A10: A-1030 | B10: Dichtschlämme 2K 15 kg | C10: 3 | D10: Eimer | E10: 2 | F10: 64 | G10: =IFERROR(C10*F10,"") -> 192 | H10: =IF(AND(ISNUMBER(C10),C10<E10),"JA","") | I10: Baustoff Kaiser
A11: A-1031 | B11: Dichtband 10 m | C11: 7 | D11: Rolle | E11: 5 | F11: 18.9 | G11: =IFERROR(C11*F11,"") -> 132.3 | H11: =IF(AND(ISNUMBER(C11),C11<E11),"JA","") | I11: Baustoff Kaiser
A12: A-1040 | B12: Tiefengrund 10 l | C12: 1 | D12: Kanister | E12: 3 | F12: 29.5 | G12: =IFERROR(C12*F12,"") -> 29.5 | H12: =IF(AND(ISNUMBER(C12),C12<E12),"JA","") -> JA | I12: Baustoff Kaiser
A13: A-1050 | B13: Abschlussprofil Alu 2,5 m | C13: 22 | D13: Stk | E13: 10 | F13: 9.8 | G13: =IFERROR(C13*F13,"") -> 215.6 | H13: =IF(AND(ISNUMBER(C13),C13<E13),"JA","") | I13: Weber KG
A14: A-1060 | B14: Feinsteinzeug 60x60 anthrazit | C14: 12,5 | D14: m² | E14: 0 | F14: 32.9 | G14: =IFERROR(C14*F14,"") | H14: =IF(AND(ISNUMBER(C14),C14<E14),"JA","") | I14: Weber KG
A15: A-1061 | B15: Wandfliese 30x60 weiß matt | C15: ca. 30 | D15: m² | E15: 0 | F15: 24.5 | G15: =IFERROR(C15*F15,"") | H15: =IF(AND(ISNUMBER(C15),C15<E15),"JA","") | I15: Weber KG
A16: A-1070 | B16: Fliesenkreuze 3 mm | C16: 9 | D16: Beutel | E16: 3 | F16: 3.9 | G16: =IFERROR(C16*F16,"") -> 35.1 | H16: =IF(AND(ISNUMBER(C16),C16<E16),"JA","") | I16: Baustoff Kaiser
A17: A-1080 | B17: Entkopplungsmatte 30 m² | C17: 2 | D17: Rolle | E17: 1 | F17: 189 | G17: =IFERROR(C17*F17,"") -> 378 | H17: =IF(AND(ISNUMBER(C17),C17<E17),"JA","") | I17: Weber KG
B19: Lagerwert gesamt | G19: =SUM(G4:G17) -> 1499.9
